bourguiba/__init__.py
bourguiba/bourguiba.py
bourguiba/instruction.py
bourguiba/model_downloader.py
bourguiba-3.1.3.dist-info/LICENSE
bourguiba-3.1.3.dist-info/METADATA
bourguiba-3.1.3.dist-info/WHEEL
bourguiba-3.1.3.dist-info/entry_points.txt
bourguiba-3.1.3.dist-info/top_level.txt
bourguiba-3.1.3.dist-info/RECORD
