Metadata-Version: 2.1
Name: bourguiba
Version: 3.1.3
Summary: Shell command generator using LLaMA model
Home-page: https://github.com/AzizBahloul/PromptToCommand
Author: Si Moahmed Aziz Bahloul, Wo Chrikou Il Mangouli Mahdi Magroun
Classifier: Programming Language :: Python :: 3
Classifier: License :: OSI Approved :: MIT License
Classifier: Operating System :: OS Independent
Requires-Python: >=3.6
License-File: LICENSE
Requires-Dist: transformers
Requires-Dist: torch
